jamaddr/JamAddr.py
jamaddr/__init__.py
jamaddr-0.5.dist-info/METADATA
jamaddr-0.5.dist-info/RECORD
jamaddr-0.5.dist-info/WHEEL
jamaddr-0.5.dist-info/top_level.txt
