Metadata-Version: 2.1
Name: jamaddr
Version: 0.5
Summary: IP Subnet package
Home-page: https://github.com/talbiston/jamaddr.git
Author: Jamison Emilio & Todd Albiston
Author-email: foxtrot711@gmail.com
License: MIT
Platform: UNKNOWN
Classifier: Programming Language :: Python :: 3 
Classifier: License :: OSI Approved :: MIT License
Classifier: Operating System :: OS Independent
